iatikit/__init__.py
iatikit/__version__.py
iatikit/data/__init__.py
iatikit/data/activity.py
iatikit/data/dataset.py
iatikit/data/organisation.py
iatikit/data/publisher.py
iatikit/data/registry.py
iatikit/data/sector.py
iatikit/standard/__init__.py
iatikit/standard/activity_schema.py
iatikit/standard/codelist.py
iatikit/standard/codelist_mappings.py
iatikit/standard/organisation_schema.py
iatikit/standard/schema.py
iatikit/standard/xsd_schema.py
iatikit/utils/__init__.py
iatikit/utils/abstract.py
iatikit/utils/config.py
iatikit/utils/download.py
iatikit/utils/exceptions.py
iatikit/utils/helpers.py
iatikit/utils/querybuilder.py
iatikit/utils/types.py
iatikit/utils/validator.py
iatikit-3.6.1.dist-info/licenses/LICENSE.md
tests/__init__.py
tests/helpers.py
tests/test_activity.py
tests/test_codelist.py
tests/test_dataset.py
tests/test_download_codelists.py
tests/test_download_data.py
tests/test_download_schemas.py
tests/test_generic_set.py
tests/test_organisation.py
tests/test_publisher.py
tests/test_registry.py
tests/test_sector.py
iatikit-3.6.1.dist-info/METADATA
iatikit-3.6.1.dist-info/WHEEL
iatikit-3.6.1.dist-info/top_level.txt
iatikit-3.6.1.dist-info/RECORD
